llama_index/embeddings/premai/__init__.py
llama_index/embeddings/premai/base.py
llama_index/embeddings/premai/pyproject.toml
llama_index/embeddings/premai/uv.lock
llama_index_embeddings_premai-0.4.1.dist-info/METADATA
llama_index_embeddings_premai-0.4.1.dist-info/WHEEL
llama_index_embeddings_premai-0.4.1.dist-info/licenses/LICENSE
llama_index_embeddings_premai-0.4.1.dist-info/RECORD
