Metadata-Version: 2.4
Name: llama-index-embeddings-premai
Version: 0.4.1
Summary: llama-index embeddings premai integration
Author: PremAI
License-Expression: MIT
License-File: LICENSE
Requires-Python: <4.0,>=3.9
Requires-Dist: llama-index-core<0.15,>=0.13.0
Requires-Dist: premai<0.4,>=0.3.20
